ansiblelint/rules/custom/ansible_lint_rules/__init__.py
ansiblelint/rules/custom/ansible_lint_rules/empty_line_between_tasks.md
ansiblelint/rules/custom/ansible_lint_rules/empty_line_between_tasks.py
ansible_lint_empty_lines_between_tasks-0.0.2.dist-info/LICENSE
ansible_lint_empty_lines_between_tasks-0.0.2.dist-info/METADATA
ansible_lint_empty_lines_between_tasks-0.0.2.dist-info/WHEEL
ansible_lint_empty_lines_between_tasks-0.0.2.dist-info/top_level.txt
ansible_lint_empty_lines_between_tasks-0.0.2.dist-info/RECORD
