Metadata-Version: 2.1
Name: ansible-lint-empty-lines-between-tasks
Version: 0.0.2
Summary: Ansible-lint rule to check for empty lines between tasks
Author-email: Martin Imre <martinimre25@gmail.com>
Project-URL: Source, https://github.com/mimre25/ansible-lint-empty-lines-between-tasks
Classifier: License :: OSI Approved :: MIT License
Classifier: Programming Language :: Python :: 3
Classifier: Programming Language :: Python :: 3 :: Only
Requires-Python: >=3.10
License-File: LICENSE
Requires-Dist: ansible-lint
Requires-Dist: typing-extensions
